cache_controller.v
// cpu interface

module cache_controller(

    input clk,
    input rst,
    input cpu_read,
    input cpu_write,

    input [7:0] cpu_addr,
    input [31:0] cpu_wdata,

    output reg [31:0] cpu_rdata,
    output reg stall_cpu
);

// cache array design
// 2-way set associative cache

reg valid [0:3][0:1];
reg dirty [0:3][0:1];

reg [3:0] tag_array [0:3][0:1];
reg [31:0] data_array [0:3][0:1];

// main memory

reg [31:0] memory [0:255];


// address breakdown

wire [1:0] index;
wire [3:0] tag;

assign index = cpu_addr[3:2];
assign tag   = cpu_addr[7:4];

// hit logic

wire hit_way0;
wire hit_way1;

assign hit_way0 =
    valid[index][0] &&
    (tag_array[index][0] == tag);

assign hit_way1 =
    valid[index][1] &&
    (tag_array[index][1] == tag);

// ----------------------------------
// FSM states
// ----------------------------------

parameter IDLE        = 2'b00;
parameter COMPARE_TAG = 2'b01;
parameter WRITE_BACK  = 2'b10;
parameter ALLOCATE    = 2'b11;

reg [1:0] state;

// ----------------------------------
// LRU logic
// ----------------------------------

reg lru [0:3];

reg replace_way;

always @(*) begin

    if(lru[index] == 0)
        replace_way = 1;
    else
        replace_way = 0;

end

// initialize memory

initial begin

    memory[8'h24] = 32'd999; // placing decimal 999 at hexadecimal address 24

end

// main FSM

integer i;
integer j;

always @(posedge clk or posedge rst) begin

    if(rst) begin

        state <= IDLE;

        stall_cpu <= 0;

        // clear cache

        for(i=0; i<4; i=i+1) begin

            for(j=0; j<2; j=j+1) begin

                valid[i][j] <= 0;
                dirty[i][j] <= 0;

            end
        end
    end

    else begin

        case(state)
        IDLE:
        begin

            if(cpu_read || cpu_write) begin

                stall_cpu <= 1;

                state <= COMPARE_TAG;

            end

        end
        COMPARE_TAG:
        begin

            // CACHE HIT WAY0

            if(hit_way0) begin

                cpu_rdata <= data_array[index][0];

                lru[index] <= 0;

                stall_cpu <= 0;

                state <= IDLE;

            end

            // CACHE HIT WAY1

            else if(hit_way1) begin

                cpu_rdata <= data_array[index][1];

                lru[index] <= 1;

                stall_cpu <= 0;

                state <= IDLE;

            end

            // CACHE MISS

            else begin

                if(dirty[index][replace_way])
                    state <= WRITE_BACK;

                else
                    state <= ALLOCATE;

            end

        end

        WRITE_BACK:
        begin

            memory[cpu_addr]
                <= data_array[index][replace_way];

            dirty[index][replace_way]
                <= 0;

            state <= ALLOCATE;

        end

        ALLOCATE:
        begin

            data_array[index][replace_way]
                <= memory[cpu_addr];

            tag_array[index][replace_way]
                <= tag;

            valid[index][replace_way]
                <= 1;

            cpu_rdata <= memory[cpu_addr];

            lru[index] <= replace_way;

            stall_cpu <= 0;

            state <= IDLE;

        end
        endcase

    end

end

endmodule

cache_controller_tb.v
module tb;

    reg clk;
    reg rst;

    reg cpu_read;
    reg cpu_write;

    reg [7:0] cpu_addr;
    reg [31:0] cpu_wdata;

    wire [31:0] cpu_rdata;
    wire stall_cpu;

    // DUT

    cache_controller uut (

        .clk(clk),
        .rst(rst),

        .cpu_read(cpu_read),
        .cpu_write(cpu_write),

        .cpu_addr(cpu_addr),
        .cpu_wdata(cpu_wdata),

        .cpu_rdata(cpu_rdata),
        .stall_cpu(stall_cpu)

    );
    // clock generation

    always #5 clk = ~clk;

    // simulation

    initial begin

        // waveform dump

        $dumpfile("dump.vcd");
        $dumpvars(0, tb);

        // initialize

        clk = 0;
        rst = 1;

        cpu_read = 0;
        cpu_write = 0;
        cpu_addr = 0;
        cpu_wdata = 0;

        // release reset

        #10;
        rst = 0;

        // CPU read request
        #10;
        cpu_read = 1;

        cpu_addr = 8'h24;

        // wait

        #10;

        cpu_read = 0;

        // finish simulation

        #100;

        $finish;

    end

endmodule

dump.vcd
$date
	Sun Jun 21 23:33:07 2026
$end
$version
	Icarus Verilog
$end
$timescale
	1s
$end
$scope module tb $end
$var wire 1 ! stall_cpu $end
$var wire 32 " cpu_rdata [31:0] $end
$var reg 1 # clk $end
$var reg 8 $ cpu_addr [7:0] $end
$var reg 1 % cpu_read $end
$var reg 32 & cpu_wdata [31:0] $end
$var reg 1 ' cpu_write $end
$var reg 1 ( rst $end
$scope module uut $end
$var wire 1 # clk $end
$var wire 8 ) cpu_addr [7:0] $end
$var wire 1 % cpu_read $end
$var wire 32 * cpu_wdata [31:0] $end
$var wire 1 ' cpu_write $end
$var wire 1 + hit_way0 $end
$var wire 1 , hit_way1 $end
$var wire 1 ( rst $end
$var wire 4 - tag [3:0] $end
$var wire 2 . index [1:0] $end
$var parameter 2 / ALLOCATE $end
$var parameter 2 0 COMPARE_TAG $end
$var parameter 2 1 IDLE $end
$var parameter 2 2 WRITE_BACK $end
$var reg 32 3 cpu_rdata [31:0] $end
$var reg 1 4 replace_way $end
$var reg 1 ! stall_cpu $end
$var reg 2 5 state [1:0] $end
$var integer 32 6 i [31:0] $end
$var integer 32 7 j [31:0] $end
$upscope $end
$upscope $end
$enddefinitions $end
$comment Show the parameter values. $end
$dumpall
b10 2
b0 1
b1 0
b11 /
$end
#0
$dumpvars
b10 7
b100 6
b0 5
04
bx 3
b0 .
b0 -
0,
0+
b0 *
b0 )
1(
0'
b0 &
0%
b0 $
0#
bx "
0!
$end
#5
b10 7
b100 6
1#
#10
0#
0(
#15
1#
#20
b1 .
b10 -
0#
b100100 $
b100100 )
1%
#25
b1 5
1!
1#
#30
0#
0%
#35
b11 5
1#
#40
0#
#45
14
1+
b0 5
0!
b1111100111 "
b1111100111 3
1#
